[
  {
    "id": "eth",
    "graph_id": "mainnet",
    "name": "Ethereum",
    "alt_names": [],
    "standard": "erc20",
    "block_type": {
      "label": "sf.ethereum.type.v2.Block",
      "url": "https://buf.build/streamingfast/firehose-ethereum/docs/main:sf.ethereum.type.v2"
    },
    "icon": {
      "id": "networks/ethereum",
      "brand_theme": "both",
      "variants": [
        "branded",
        "mono"
      ]
    },
    "supported_services": {
      "firehose": {
        "released_at": "2023-12-01T00:00:00.000Z",
        "deprecated_at": null
      },
      "substreams": {
        "released_at": "2023-12-01T00:00:00.000Z",
        "deprecated_at": null
      },
      "rpc": {
        "released_at": "2023-12-01T00:00:00.000Z",
        "deprecated_at": null
      }
    },
    "index": 0,
    "testnets": [
      {
        "id": "holesky",
        "graph_id": null,
        "name": "Holesky",
        "alt_names": [],
        "supported_services": {
          "firehose": {
            "released_at": "2023-12-01T00:00:00.000Z",
            "deprecated_at": null
          },
          "substreams": {
            "released_at": "2023-12-01T00:00:00.000Z",
            "deprecated_at": null
          },
          "rpc": {
            "released_at": "2023-12-01T00:00:00.000Z",
            "deprecated_at": null
          }
        },
        "index": 1
      },
      {
        "id": "sepolia",
        "graph_id": "sepolia",
        "name": "Sepolia",
        "alt_names": [],
        "supported_services": {
          "firehose": {
            "released_at": "2023-12-01T00:00:00.000Z",
            "deprecated_at": null
          },
          "substreams": {
            "released_at": "2023-12-01T00:00:00.000Z",
            "deprecated_at": null
          },
          "rpc": {
            "released_at": "2023-12-01T00:00:00.000Z",
            "deprecated_at": null
          }
        },
        "index": 2
      }
    ],
    "consensus_layers": [
      {
        "id": "eth-cl",
        "graph_id": null,
        "name": "Ethereum Consensus Layer",
        "alt_names": [],
        "supported_services": {
          "firehose": {
            "released_at": null,
            "deprecated_at": null
          },
          "substreams": {
            "released_at": "2023-03-08T00:00:00.000Z",
            "deprecated_at": null
          },
          "rpc": {
            "released_at": null,
            "deprecated_at": null
          }
        },
        "index": 3
      },
      {
        "id": "holesky-cl",
        "graph_id": null,
        "name": "Holesky Consensus Layer",
        "alt_names": [],
        "supported_services": {
          "firehose": {
            "released_at": null,
            "deprecated_at": null
          },
          "substreams": {
            "released_at": "2023-03-08T00:00:00.000Z",
            "deprecated_at": null
          },
          "rpc": {
            "released_at": null,
            "deprecated_at": null
          }
        },
        "index": 4
      },
      {
        "id": "sepolia-cl",
        "graph_id": null,
        "name": "Sepolia Consensus Layer",
        "alt_names": [],
        "supported_services": {
          "firehose": {
            "released_at": null,
            "deprecated_at": null
          },
          "substreams": {
            "released_at": "2023-03-08T00:00:00.000Z",
            "deprecated_at": null
          },
          "rpc": {
            "released_at": null,
            "deprecated_at": null
          }
        },
        "index": 5
      }
    ]
  },
  {
    "id": "bitcoin",
    "graph_id": null,
    "name": "Bitcoin",
    "alt_names": [
      "btc"
    ],
    "standard": "brc20",
    "block_type": {
      "label": "sf.bitcoin.type.v1.Block",
      "url": "https://buf.build/streamingfast/firehose-bitcoin/docs/main:sf.bitcoin.type.v1"
    },
    "icon": {
      "id": "tokens/bitcoin",
      "brand_theme": "both",
      "variants": [
        "branded",
        "mono"
      ]
    },
    "supported_services": {
      "firehose": {
        "released_at": "2023-12-21T00:00:00.000Z",
        "deprecated_at": null
      },
      "substreams": {
        "released_at": "2023-12-21T00:00:00.000Z",
        "deprecated_at": null
      },
      "rpc": {
        "released_at": null,
        "deprecated_at": null
      }
    },
    "index": 1000
  },
  {
    "id": "polygon",
    "graph_id": "matic",
    "name": "Polygon",
    "alt_names": [
      "matic"
    ],
    "standard": "erc20",
    "block_type": {
      "label": "sf.ethereum.type.v2.Block",
      "url": "https://buf.build/streamingfast/firehose-ethereum/docs/main:sf.ethereum.type.v2"
    },
    "icon": {
      "id": "tokens/matic-network",
      "brand_theme": "both",
      "variants": [
        "branded",
        "mono"
      ]
    },
    "supported_services": {
      "firehose": {
        "released_at": "2023-12-01T00:00:00.000Z",
        "deprecated_at": null
      },
      "substreams": {
        "released_at": "2023-12-01T00:00:00.000Z",
        "deprecated_at": null
      },
      "rpc": {
        "released_at": "2023-12-01T00:00:00.000Z",
        "deprecated_at": null
      }
    },
    "index": 2000,
    "testnets": [
      {
        "id": "mumbai",
        "graph_id": "mumbai",
        "name": "Mumbai",
        "alt_names": [],
        "supported_services": {
          "firehose": {
            "released_at": "2023-12-01T00:00:00.000Z",
            "deprecated_at": null
          },
          "substreams": {
            "released_at": "2023-12-01T00:00:00.000Z",
            "deprecated_at": null
          },
          "rpc": {
            "released_at": "2023-12-01T00:00:00.000Z",
            "deprecated_at": null
          }
        },
        "index": 2001
      }
    ]
  },
  {
    "id": "bsc",
    "graph_id": "bsc",
    "name": "BNB",
    "alt_names": [
      "bsc",
      "binance"
    ],
    "standard": "erc20",
    "block_type": {
      "label": "sf.ethereum.type.v2.Block",
      "url": "https://buf.build/streamingfast/firehose-ethereum/docs/main:sf.ethereum.type.v2"
    },
    "icon": {
      "id": "networks/binance-smart-chain",
      "brand_theme": "both",
      "variants": [
        "branded",
        "mono"
      ]
    },
    "supported_services": {
      "firehose": {
        "released_at": "2023-12-01T00:00:00.000Z",
        "deprecated_at": null
      },
      "substreams": {
        "released_at": "2023-12-01T00:00:00.000Z",
        "deprecated_at": null
      },
      "rpc": {
        "released_at": "2023-12-01T00:00:00.000Z",
        "deprecated_at": null
      }
    },
    "index": 3000,
    "testnets": [
      {
        "id": "chapel",
        "graph_id": "chapel",
        "name": "Chapel",
        "alt_names": [],
        "supported_services": {
          "firehose": {
            "released_at": "2023-12-01T00:00:00.000Z",
            "deprecated_at": null
          },
          "substreams": {
            "released_at": "2023-12-01T00:00:00.000Z",
            "deprecated_at": null
          },
          "rpc": {
            "released_at": "2023-12-01T00:00:00.000Z",
            "deprecated_at": null
          }
        },
        "index": 3001
      }
    ]
  },
  {
    "id": "arbone",
    "graph_id": "arbitrum-one",
    "name": "Arbitrum One",
    "alt_names": [],
    "standard": "erc20",
    "block_type": {
      "label": "sf.ethereum.type.v2.Block",
      "url": "https://buf.build/streamingfast/firehose-ethereum/docs/main:sf.ethereum.type.v2"
    },
    "icon": {
      "id": "tokens/arbitrum",
      "brand_theme": "both",
      "variants": [
        "mono"
      ]
    },
    "supported_services": {
      "firehose": {
        "released_at": null,
        "deprecated_at": null
      },
      "substreams": {
        "released_at": null,
        "deprecated_at": null
      },
      "rpc": {
        "released_at": null,
        "deprecated_at": null
      }
    },
    "index": 4000,
    "testnets": [
      {
        "id": "arbgoerli",
        "graph_id": "arbitrum-goerli",
        "name": "Arbitrum Goerli",
        "alt_names": [],
        "supported_services": {
          "firehose": {
            "released_at": null,
            "deprecated_at": null
          },
          "substreams": {
            "released_at": null,
            "deprecated_at": null
          },
          "rpc": {
            "released_at": null,
            "deprecated_at": null
          }
        },
        "index": 4001
      },
      {
        "id": "arbsepolia",
        "graph_id": "arbitrum-sepolia",
        "name": "Arbitrum Sepolia",
        "alt_names": [],
        "supported_services": {
          "firehose": {
            "released_at": null,
            "deprecated_at": null
          },
          "substreams": {
            "released_at": null,
            "deprecated_at": null
          },
          "rpc": {
            "released_at": null,
            "deprecated_at": null
          }
        },
        "index": 4002
      },
      {
        "id": "chiado",
        "graph_id": null,
        "name": "Chiado",
        "alt_names": [],
        "supported_services": {
          "firehose": {
            "released_at": null,
            "deprecated_at": null
          },
          "substreams": {
            "released_at": null,
            "deprecated_at": null
          },
          "rpc": {
            "released_at": null,
            "deprecated_at": null
          }
        },
        "index": 4004
      }
    ],
    "consensus_layers": [
      {
        "id": "chiado-cl",
        "graph_id": null,
        "name": "Chiado Consensus Layer",
        "alt_names": [],
        "supported_services": {
          "firehose": {
            "released_at": null,
            "deprecated_at": null
          },
          "substreams": {
            "released_at": "2023-03-08T00:00:00.000Z",
            "deprecated_at": null
          },
          "rpc": {
            "released_at": null,
            "deprecated_at": null
          }
        },
        "index": 4003
      }
    ]
  },
  {
    "id": "optimism",
    "graph_id": "optimism",
    "name": "Optimism",
    "alt_names": [],
    "standard": "erc20",
    "block_type": {
      "label": "sf.ethereum.type.v2.Block",
      "url": "https://buf.build/streamingfast/firehose-ethereum/docs/main:sf.ethereum.type.v2"
    },
    "icon": {
      "id": "tokens/optimism",
      "brand_theme": "both",
      "variants": [
        "branded",
        "mono"
      ]
    },
    "supported_services": {
      "firehose": {
        "released_at": "2024-01-01T00:00:00.000Z",
        "deprecated_at": null
      },
      "substreams": {
        "released_at": "2024-01-01T00:00:00.000Z",
        "deprecated_at": null
      },
      "rpc": {
        "released_at": null,
        "deprecated_at": null
      }
    },
    "index": 5000
  },
  {
    "id": "base",
    "graph_id": "base",
    "name": "Base",
    "alt_names": [],
    "standard": "erc20",
    "block_type": {
      "label": "sf.ethereum.type.v2.Block",
      "url": "https://buf.build/streamingfast/firehose-ethereum/docs/main:sf.ethereum.type.v2"
    },
    "icon": {
      "id": "tokens/base",
      "brand_theme": "both",
      "variants": [
        "branded",
        "mono"
      ]
    },
    "supported_services": {
      "firehose": {
        "released_at": "2024-03-06T00:00:00.000Z",
        "deprecated_at": null
      },
      "substreams": {
        "released_at": "2024-03-06T00:00:00.000Z",
        "deprecated_at": null
      },
      "rpc": {
        "released_at": null,
        "deprecated_at": null
      }
    },
    "index": 6000
  },
  {
    "id": "gnosis",
    "graph_id": "gnosis",
    "name": "Gnosis",
    "alt_names": [],
    "standard": "erc20",
    "block_type": {
      "label": "sf.ethereum.type.v2.Block",
      "url": "https://buf.build/streamingfast/firehose-ethereum/docs/main:sf.ethereum.type.v2"
    },
    "icon": {
      "id": "tokens/gnosis",
      "brand_theme": "dark",
      "variants": [
        "branded",
        "mono"
      ]
    },
    "supported_services": {
      "firehose": {
        "released_at": null,
        "deprecated_at": null
      },
      "substreams": {
        "released_at": null,
        "deprecated_at": null
      },
      "rpc": {
        "released_at": null,
        "deprecated_at": null
      }
    },
    "index": 7000,
    "consensus_layers": [
      {
        "id": "gnosis-cl",
        "graph_id": null,
        "name": "Gnosis Consensus Layer",
        "alt_names": [],
        "supported_services": {
          "firehose": {
            "released_at": null,
            "deprecated_at": null
          },
          "substreams": {
            "released_at": "2023-03-08T00:00:00.000Z",
            "deprecated_at": null
          },
          "rpc": {
            "released_at": null,
            "deprecated_at": null
          }
        },
        "index": 7001
      }
    ]
  },
  {
    "id": "celo",
    "graph_id": "celo",
    "name": "Celo",
    "alt_names": [],
    "standard": "erc20",
    "block_type": {
      "label": "sf.ethereum.type.v2.Block",
      "url": "https://buf.build/streamingfast/firehose-ethereum/docs/main:sf.ethereum.type.v2"
    },
    "icon": {
      "id": "networks/celo",
      "brand_theme": "light",
      "variants": [
        "branded",
        "mono"
      ]
    },
    "supported_services": {
      "firehose": {
        "released_at": null,
        "deprecated_at": null
      },
      "substreams": {
        "released_at": null,
        "deprecated_at": null
      },
      "rpc": {
        "released_at": null,
        "deprecated_at": null
      }
    },
    "index": 8000,
    "testnets": [
      {
        "id": "alfajores",
        "graph_id": null,
        "name": "Alfajores",
        "alt_names": [],
        "supported_services": {
          "firehose": {
            "released_at": null,
            "deprecated_at": null
          },
          "substreams": {
            "released_at": null,
            "deprecated_at": null
          },
          "rpc": {
            "released_at": null,
            "deprecated_at": null
          }
        },
        "index": 8001
      }
    ]
  },
  {
    "id": "near",
    "graph_id": "near-mainnet",
    "name": "Near",
    "alt_names": [],
    "standard": "near",
    "block_type": {
      "label": "sf.near.type.v1.Block",
      "url": "https://buf.build/streamingfast/firehose-near/docs/main:sf.near.type.v1"
    },
    "icon": {
      "id": "tokens/near",
      "brand_theme": "both",
      "variants": [
        "branded",
        "mono"
      ]
    },
    "supported_services": {
      "firehose": {
        "released_at": "2023-12-01T00:00:00.000Z",
        "deprecated_at": null
      },
      "substreams": {
        "released_at": "2023-12-01T00:00:00.000Z",
        "deprecated_at": null
      },
      "rpc": {
        "released_at": null,
        "deprecated_at": null
      }
    },
    "index": 9000,
    "testnets": [
      {
        "id": "neartest",
        "graph_id": "near-testnet",
        "name": "Near-testnet",
        "alt_names": [],
        "supported_services": {
          "firehose": {
            "released_at": "2023-12-01T00:00:00.000Z",
            "deprecated_at": null
          },
          "substreams": {
            "released_at": "2023-12-01T00:00:00.000Z",
            "deprecated_at": null
          },
          "rpc": {
            "released_at": null,
            "deprecated_at": null
          }
        },
        "index": 9001
      }
    ]
  },
  {
    "id": "arweave",
    "graph_id": "arweave-mainnet",
    "name": "Arweave",
    "alt_names": [],
    "standard": "erc20",
    "block_type": {
      "label": "sf.arweave.type.v1.Block",
      "url": "https://buf.build/pinax/firehose-arweave/docs/main:sf.arweave.type.v1"
    },
    "icon": {
      "id": "tokens/arweave",
      "brand_theme": "dark",
      "variants": [
        "branded",
        "mono"
      ]
    },
    "supported_services": {
      "firehose": {
        "released_at": "2023-12-01T00:00:00.000Z",
        "deprecated_at": null
      },
      "substreams": {
        "released_at": "2024-03-03T00:00:00.000Z",
        "deprecated_at": null
      },
      "rpc": {
        "released_at": null,
        "deprecated_at": null
      }
    },
    "index": 10000
  },
  {
    "id": "cosmoshub",
    "graph_id": "cosmoshub-4",
    "name": "Cosmos Hub",
    "alt_names": [],
    "standard": "cosmos",
    "block_type": {
      "label": "sf.cosmos.type.v1.Block",
      "url": "https://github.com/figment-networks/proto-cosmos/blob/main/sf/cosmos/type/v1/type.proto"
    },
    "icon": {
      "id": "networks/cosmos",
      "brand_theme": "dark",
      "variants": [
        "branded",
        "mono"
      ]
    },
    "supported_services": {
      "firehose": {
        "released_at": "2023-12-01T00:00:00.000Z",
        "deprecated_at": null
      },
      "substreams": {
        "released_at": null,
        "deprecated_at": null
      },
      "rpc": {
        "released_at": null,
        "deprecated_at": null
      }
    },
    "index": 11000,
    "testnets": [
      {
        "id": "theta",
        "graph_id": "theta-testnet-001",
        "name": "Theta",
        "alt_names": [],
        "supported_services": {
          "firehose": {
            "released_at": "2023-12-01T00:00:00.000Z",
            "deprecated_at": null
          },
          "substreams": {
            "released_at": "2023-12-01T00:00:00.000Z",
            "deprecated_at": null
          },
          "rpc": {
            "released_at": null,
            "deprecated_at": null
          }
        },
        "index": 11001
      }
    ]
  },
  {
    "id": "osmosis",
    "graph_id": "osmosis-1",
    "name": "Osmosis",
    "alt_names": [],
    "standard": "cosmos",
    "block_type": {
      "label": "sf.cosmos.type.v1.Block",
      "url": "https://github.com/figment-networks/proto-cosmos/blob/main/sf/cosmos/type/v1/type.proto"
    },
    "icon": {
      "id": "tokens/osmosis",
      "brand_theme": "both",
      "variants": [
        "branded",
        "mono"
      ]
    },
    "supported_services": {
      "firehose": {
        "released_at": "2023-12-01T00:00:00.000Z",
        "deprecated_at": null
      },
      "substreams": {
        "released_at": null,
        "deprecated_at": null
      },
      "rpc": {
        "released_at": null,
        "deprecated_at": null
      }
    },
    "index": 12000
  },
  {
    "id": "eos",
    "graph_id": null,
    "name": "EOS",
    "alt_names": [],
    "standard": "antelope",
    "block_type": {
      "label": "sf.antelope.type.v1.Block",
      "url": "https://buf.build/pinax/firehose-antelope/docs/main:sf.antelope.type.v1"
    },
    "icon": {
      "id": "networks/eos",
      "brand_theme": "TBD"
    },
    "supported_services": {
      "firehose": {
        "released_at": "2023-12-01T00:00:00.000Z",
        "deprecated_at": null
      },
      "substreams": {
        "released_at": "2023-12-01T00:00:00.000Z",
        "deprecated_at": null
      },
      "rpc": {
        "released_at": null,
        "deprecated_at": null
      }
    },
    "index": 13000,
    "testnets": [
      {
        "id": "jungle4",
        "graph_id": null,
        "name": "Jungle4",
        "alt_names": [],
        "supported_services": {
          "firehose": {
            "released_at": "2023-12-01T00:00:00.000Z",
            "deprecated_at": null
          },
          "substreams": {
            "released_at": "2023-12-01T00:00:00.000Z",
            "deprecated_at": null
          },
          "rpc": {
            "released_at": "2023-12-01T00:00:00.000Z",
            "deprecated_at": null
          }
        },
        "index": 13001
      },
      {
        "id": "kylin",
        "graph_id": null,
        "name": "Kylin",
        "alt_names": [],
        "supported_services": {
          "firehose": {
            "released_at": "2023-12-01T00:00:00.000Z",
            "deprecated_at": null
          },
          "substreams": {
            "released_at": "2023-12-01T00:00:00.000Z",
            "deprecated_at": null
          },
          "rpc": {
            "released_at": null,
            "deprecated_at": null
          }
        },
        "index": 13002
      }
    ]
  },
  {
    "id": "wax",
    "graph_id": null,
    "name": "WAX",
    "alt_names": [],
    "standard": "antelope",
    "block_type": {
      "label": "sf.antelope.type.v1.Block",
      "url": "https://buf.build/pinax/firehose-antelope/docs/main:sf.antelope.type.v1"
    },
    "icon": {
      "id": "tokens/wax",
      "brand_theme": "both",
      "variants": [
        "branded",
        "mono"
      ]
    },
    "supported_services": {
      "firehose": {
        "released_at": "2023-12-01T00:00:00.000Z",
        "deprecated_at": null
      },
      "substreams": {
        "released_at": "2023-12-01T00:00:00.000Z",
        "deprecated_at": null
      },
      "rpc": {
        "released_at": null,
        "deprecated_at": null
      }
    },
    "index": 14000,
    "testnets": [
      {
        "id": "waxtest",
        "graph_id": null,
        "name": "WAX Test",
        "alt_names": [],
        "supported_services": {
          "firehose": {
            "released_at": "2023-12-01T00:00:00.000Z",
            "deprecated_at": null
          },
          "substreams": {
            "released_at": "2023-12-01T00:00:00.000Z",
            "deprecated_at": null
          },
          "rpc": {
            "released_at": null,
            "deprecated_at": null
          }
        },
        "index": 14001
      }
    ]
  },
  {
    "id": "telos",
    "graph_id": null,
    "name": "Telos",
    "alt_names": [],
    "standard": "antelope",
    "block_type": {
      "label": "sf.antelope.type.v1.Block",
      "url": "https://buf.build/pinax/firehose-antelope/docs/main:sf.antelope.type.v1"
    },
    "icon": {
      "id": "networks/telos",
      "brand_theme": "both",
      "variants": [
        "branded",
        "mono"
      ]
    },
    "supported_services": {
      "firehose": {
        "released_at": "2023-12-01T00:00:00.000Z",
        "deprecated_at": null
      },
      "substreams": {
        "released_at": "2023-12-01T00:00:00.000Z",
        "deprecated_at": null
      },
      "rpc": {
        "released_at": null,
        "deprecated_at": null
      }
    },
    "index": 15000,
    "testnets": [
      {
        "id": "telostest",
        "graph_id": null,
        "name": "Telos Test",
        "alt_names": [],
        "supported_services": {
          "firehose": {
            "released_at": "2023-12-01T00:00:00.000Z",
            "deprecated_at": null
          },
          "substreams": {
            "released_at": "2023-12-01T00:00:00.000Z",
            "deprecated_at": null
          },
          "rpc": {
            "released_at": null,
            "deprecated_at": null
          }
        },
        "index": 15001
      }
    ]
  },
  {
    "id": "avalanche",
    "graph_id": "avalanche",
    "name": "Avalanche",
    "alt_names": [],
    "standard": "erc20",
    "block_type": {
      "label": "sf.ethereum.type.v2.Block",
      "url": "https://buf.build/streamingfast/firehose-ethereum/docs/main:sf.ethereum.type.v2"
    },
    "icon": {
      "id": "networks/avalanche",
      "brand_theme": "both",
      "variants": [
        "branded",
        "mono"
      ]
    },
    "supported_services": {
      "firehose": {
        "released_at": null,
        "deprecated_at": null
      },
      "substreams": {
        "released_at": null,
        "deprecated_at": null
      },
      "rpc": {
        "released_at": null,
        "deprecated_at": null
      }
    },
    "index": 16000
  },
  {
    "id": "fantom",
    "graph_id": "fantom",
    "name": "Fantom",
    "alt_names": [],
    "standard": "erc20",
    "block_type": {
      "label": "sf.ethereum.type.v2.Block",
      "url": "https://buf.build/streamingfast/firehose-ethereum/docs/main:sf.ethereum.type.v2"
    },
    "icon": {
      "id": "networks/fantom",
      "brand_theme": "light",
      "variants": [
        "branded",
        "mono"
      ]
    },
    "supported_services": {
      "firehose": {
        "released_at": null,
        "deprecated_at": null
      },
      "substreams": {
        "released_at": null,
        "deprecated_at": null
      },
      "rpc": {
        "released_at": null,
        "deprecated_at": null
      }
    },
    "index": 17000
  },
  {
    "id": "moonbeam",
    "graph_id": "moonbeam",
    "name": "Moonbeam",
    "alt_names": [],
    "standard": "erc20",
    "block_type": {
      "label": "sf.ethereum.type.v2.Block",
      "url": "https://buf.build/streamingfast/firehose-ethereum/docs/main:sf.ethereum.type.v2"
    },
    "icon": {
      "id": "networks/moonbeam",
      "brand_theme": "both",
      "variants": [
        "branded",
        "mono"
      ]
    },
    "supported_services": {
      "firehose": {
        "released_at": null,
        "deprecated_at": null
      },
      "substreams": {
        "released_at": null,
        "deprecated_at": null
      },
      "rpc": {
        "released_at": null,
        "deprecated_at": null
      }
    },
    "index": 18000
  },
  {
    "id": "scroll",
    "graph_id": "scroll",
    "name": "Scroll",
    "alt_names": [],
    "standard": "erc20",
    "block_type": {
      "label": "sf.ethereum.type.v2.Block",
      "url": "https://buf.build/streamingfast/firehose-ethereum/docs/main:sf.ethereum.type.v2"
    },
    "icon": {
      "id": "networks/scroll",
      "brand_theme": "both",
      "variants": [
        "branded",
        "mono"
      ]
    },
    "supported_services": {
      "firehose": {
        "released_at": null,
        "deprecated_at": null
      },
      "substreams": {
        "released_at": null,
        "deprecated_at": null
      },
      "rpc": {
        "released_at": null,
        "deprecated_at": null
      }
    },
    "index": 19000
  },
  {
    "id": "decimal",
    "graph_id": null,
    "name": "Decimal",
    "alt_names": [],
    "standard": "erc20",
    "block_type": {
      "label": "sf.ethereum.type.v2.Block",
      "url": "https://buf.build/streamingfast/firehose-ethereum/docs/main:sf.ethereum.type.v2"
    },
    "icon": {
      "id": "tokens/decimal",
      "brand_theme": "both",
      "variants": [
        "branded",
        "mono"
      ]
    },
    "supported_services": {
      "firehose": {
        "released_at": null,
        "deprecated_at": null
      },
      "substreams": {
        "released_at": null,
        "deprecated_at": null
      },
      "rpc": {
        "released_at": null,
        "deprecated_at": null
      }
    },
    "index": 20000
  },
  {
    "id": "kava",
    "graph_id": null,
    "name": "Kava",
    "alt_names": [],
    "standard": "erc20",
    "block_type": {
      "label": "sf.ethereum.type.v2.Block",
      "url": "https://buf.build/streamingfast/firehose-ethereum/docs/main:sf.ethereum.type.v2"
    },
    "icon": {
      "id": "networks/kava",
      "brand_theme": "both",
      "variants": [
        "branded",
        "mono"
      ]
    },
    "supported_services": {
      "firehose": {
        "released_at": null,
        "deprecated_at": null
      },
      "substreams": {
        "released_at": null,
        "deprecated_at": null
      },
      "rpc": {
        "released_at": null,
        "deprecated_at": null
      }
    },
    "index": 21000
  },
  {
    "id": "starknet",
    "graph_id": null,
    "name": "Starknet",
    "alt_names": [],
    "standard": "erc20",
    "block_type": {
      "label": "sf.ethereum.type.v2.Block",
      "url": "https://buf.build/streamingfast/firehose-ethereum/docs/main:sf.ethereum.type.v2"
    },
    "icon": {
      "id": "networks/starknet",
      "brand_theme": "both",
      "variants": [
        "branded",
        "mono"
      ]
    },
    "supported_services": {
      "firehose": {
        "released_at": null,
        "deprecated_at": null
      },
      "substreams": {
        "released_at": null,
        "deprecated_at": null
      },
      "rpc": {
        "released_at": null,
        "deprecated_at": null
      }
    },
    "index": 22000
  }
]